{
  "name": "yasync",
  "url": "https://github.com/yglukhov/yasync",
  "method": "git",
  "description": "Yet another async/await for Nim",
  "license": "MIT",
  "web": "https://github.com/yglukhov/yasync",
  "tags": [
    "async",
    "futures"
  ],
  "meta": {
    "nimble": {
      "version": "0.1.0",
      "requires": [
        {
          "name": "nim",
          "str": ">= 2.2",
          "ver": {
            "kind": "verEqLater",
            "ver": "2.2"
          }
        }
      ],
      "bin": [],
      "srcDir": ""
    },
    "commit": {
      "hash": "e25284ff20fabe53b7f42150c90b72bc03dc2e0f",
      "time": 1768404066
    }
  }
}