{
  "name": "stdx",
  "url": "https://github.com/jjv360/nim-stdx",
  "method": "git",
  "description": "A collection of extra utilities for Nim.",
  "license": "MIT",
  "web": "https://github.com/jjv360/nim-stdx",
  "tags": [
    "std",
    "standard",
    "lib",
    "library",
    "extras",
    "stdx"
  ],
  "meta": {
    "nimble": {
      "version": "0.2.3",
      "requires": [
        {
          "name": "nim",
          "str": ">= 2.0.0",
          "ver": {
            "kind": "verEqLater",
            "ver": "2.0.0"
          }
        },
        {
          "name": "semver",
          "str": ">= 1.2.1",
          "ver": {
            "kind": "verEqLater",
            "ver": "1.2.1"
          }
        },
        {
          "name": "winim",
          "str": ">= 3.9.1",
          "ver": {
            "kind": "verEqLater",
            "ver": "3.9.1"
          }
        }
      ],
      "bin": [],
      "srcDir": "src"
    },
    "versions": [
      {
        "tag": "v0.2.3",
        "hash": "7364da5eb8f0550252adce9a0d058d0ba3351666",
        "time": 1694708786
      },
      {
        "tag": "v0.1.2",
        "hash": "6d6da89ab0db89ae1bf31e0408a304fa822326b3",
        "time": 1694335601
      }
    ],
    "commit": {
      "hash": "b51ad662b68915cc56180eb9472c258254f814c0",
      "time": 1698599885
    }
  }
}