{
  "name": "streamhttp",
  "url": "https://github.com/capocasa/streamhttp",
  "method": "git",
  "description": "Tiny synchronous streaming HTTP/1.1 client. Reads chunked bodies as they arrive.",
  "license": "MIT",
  "web": "https://github.com/capocasa/streamhttp",
  "tags": [
    "http",
    "client",
    "streaming",
    "sse",
    "chunked",
    "tls"
  ],
  "meta": {
    "nimble": {
      "version": "0.3.1",
      "requires": [
        {
          "name": "nim",
          "str": ">= 2.0.0",
          "ver": {
            "kind": "verEqLater",
            "ver": "2.0.0"
          }
        }
      ],
      "bin": [],
      "srcDir": "src"
    },
    "versions": [
      {
        "tag": "0.3.1",
        "hash": "7fdc6afed529d38c991d4898dc518d47d50d3597",
        "time": 1782600912
      },
      {
        "tag": "0.2.1",
        "hash": "bb002ddc36fff55898c07ed97f353c3feff7205f",
        "time": 1782480675
      },
      {
        "tag": "0.1.3",
        "hash": "0570ba6c387f6478b0c7fd9872d7aee788a74db7",
        "time": 1781810630
      },
      {
        "tag": "0.1.2",
        "hash": "e22c99fd6e61748cd468aec1414fb415c8d0515e",
        "time": 1777620149
      },
      {
        "tag": "0.1.1",
        "hash": "397ab35608ccc7834292c147bb34dfd2adb720fd",
        "time": 1777550744
      },
      {
        "tag": "0.1.0",
        "hash": "8ee5c102ddf3aa794caf619795a58cc261c0b132",
        "time": 1777543445
      }
    ],
    "commit": {
      "hash": "7fdc6afed529d38c991d4898dc518d47d50d3597",
      "time": 1782600912
    }
  }
}