{
  "name": "sdl2",
  "url": "https://github.com/nim-lang/sdl2",
  "method": "git",
  "description": "Wrapper for SDL 2.x",
  "license": "MIT",
  "web": "https://github.com/nim-lang/sdl2",
  "tags": [
    "wrapper",
    "media",
    "audio",
    "video"
  ],
  "meta": {
    "nimble": {
      "version": "2.0.5",
      "requires": [
        {
          "name": "nim",
          "str": ">= 0.12.0",
          "ver": {
            "kind": "verEqLater",
            "ver": "0.12.0"
          }
        }
      ],
      "bin": [],
      "srcDir": "src"
    },
    "versions": [
      {
        "tag": "v2.0.5",
        "hash": "84d4702e838d684b7304882ffe796f57ef422fb6",
        "time": 1685889510
      },
      {
        "tag": "v2.0.4",
        "hash": "4b42141b97ee7683029de0f4e2ae3dc74d63bad7",
        "time": 1660203835
      },
      {
        "tag": "v2.0.3",
        "hash": "e084923c35e6f513240456d87b3cc9cfd2081e91",
        "time": 1617058617
      },
      {
        "tag": "v2.0.2",
        "hash": "4d74e4fc97394bc47da3e8415887f6a7a96891bf",
        "time": 1572905085
      },
      {
        "tag": "v2.0.1",
        "hash": "6ad2bbf2b6cecda7b18eb48d438bb6bca8ba7180",
        "time": 1565539157
      },
      {
        "tag": "v2.0",
        "hash": "f1f2d147bc32dee2111696483812337e7ec15ed6",
        "time": 1541621103
      }
    ],
    "commit": {
      "hash": "82eb32f8c56fb53761d9ccf7ed547f40bef0a271",
      "time": 1769672354
    }
  }
}