{
  "name": "rz",
  "url": "https://github.com/hmbemba/rz",
  "method": "git",
  "description": "rz: small Result/Rz type + safe helpers (native + JS), ergonomic combinators and utilities.",
  "license": "MIT",
  "web": "https://github.com/hmbemba/rz",
  "tags": [
    "result"
  ],
  "meta": {
    "nimble": {
      "version": "0.1.1",
      "requires": [
        {
          "name": "nim",
          "str": ">= 2.0.0",
          "ver": {
            "kind": "verEqLater",
            "ver": "2.0.0"
          }
        },
        {
          "name": "ic",
          "str": ">= 0.1.0",
          "ver": {
            "kind": "verEqLater",
            "ver": "0.1.0"
          }
        }
      ],
      "bin": [],
      "srcDir": "src"
    },
    "versions": [
      {
        "tag": "v0.1.1",
        "hash": "c732bb0e6f8d2390ea2c2280ecd680185610ecda",
        "time": 1771635247
      }
    ],
    "commit": {
      "hash": "c732bb0e6f8d2390ea2c2280ecd680185610ecda",
      "time": 1771635247
    },
    "status": "Unknown"
  }
}