{
  "name": "cobs",
  "url": "https://github.com/keyme/nim_cobs",
  "method": "git",
  "description": "Consistent Overhead Byte Stuffing for Nim",
  "license": "MIT",
  "web": "https://github.com/keyme/nim_cobs",
  "tags": [
    "serialization",
    "encoding",
    "wireline",
    "framing",
    "cobs"
  ],
  "meta": {
    "nimble": {
      "version": "1.0.0",
      "requires": [
        {
          "name": "nim",
          "str": ">= 0.18.0",
          "ver": {
            "kind": "verEqLater",
            "ver": "0.18.0"
          }
        }
      ],
      "bin": [],
      "srcDir": "src"
    },
    "commit": {
      "hash": "a2fa5ab0bca493e5b0c0806f5b0c3fbfda76fa23",
      "time": 1522777427
    }
  }
}