{
  "name": "booyaka",
  "url": "https://github.com/openpeeps/booyaka",
  "method": "git",
  "description": "A fast documentation generator for cool kids!",
  "license": "AGPL-3.0-or-later",
  "web": "https://github.com/openpeeps/booyaka",
  "tags": [
    "docs",
    "documentation",
    "build",
    "builder",
    "generator",
    "markdown",
    "md",
    "devtool"
  ],
  "meta": {
    "nimble": {
      "version": "0.1.0",
      "requires": [
        {
          "name": "nim",
          "str": ">= 2.0.0",
          "ver": {
            "kind": "verEqLater",
            "ver": "2.0.0"
          }
        },
        {
          "name": "supranim",
          "str": ">= 0.1.0",
          "ver": {
            "kind": "verEqLater",
            "ver": "0.1.0"
          }
        },
        {
          "name": "tim",
          "str": ">= 0.2.1",
          "ver": {
            "kind": "verEqLater",
            "ver": "0.2.1"
          }
        },
        {
          "name": "limiter",
          "str": ">= 0.1.0",
          "ver": {
            "kind": "verEqLater",
            "ver": "0.1.0"
          }
        },
        {
          "name": "marvdown",
          "str": ">= 0.1.0",
          "ver": {
            "kind": "verEqLater",
            "ver": "0.1.0"
          }
        },
        {
          "name": "jsony",
          "str": ">= 1.1.6",
          "ver": {
            "kind": "verEqLater",
            "ver": "1.1.6"
          }
        },
        {
          "name": "flatty",
          "str": ">= 0.4.0",
          "ver": {
            "kind": "verEqLater",
            "ver": "0.4.0"
          }
        },
        {
          "name": "semver",
          "str": ">= 1.2.3",
          "ver": {
            "kind": "verEqLater",
            "ver": "1.2.3"
          }
        },
        {
          "name": "iconim",
          "str": ">= 0.1.0",
          "ver": {
            "kind": "verEqLater",
            "ver": "0.1.0"
          }
        },
        {
          "name": "pluginkit",
          "str": ">= 0.1.0",
          "ver": {
            "kind": "verEqLater",
            "ver": "0.1.0"
          }
        },
        {
          "name": "openparser",
          "str": ">= 0.1.2",
          "ver": {
            "kind": "verEqLater",
            "ver": "0.1.2"
          }
        },
        {
          "name": "supra",
          "str": ">= 0.1.0",
          "ver": {
            "kind": "verEqLater",
            "ver": "0.1.0"
          }
        }
      ],
      "bin": [
        "booyaka"
      ],
      "srcDir": "src"
    },
    "hasBin": true,
    "commit": {
      "hash": "6aab2d8b37d9b422ef4229165b08f9eb78118f18",
      "time": 1782555683
    }
  }
}