{
  "name": "distributions",
  "url": "https://github.com/ayman-albaz/distributions",
  "method": "git",
  "description": "Distributions is a Nim library for distributions and their functions.",
  "license": "Apache-2.0 License",
  "web": "https://github.com/ayman-albaz/distributions",
  "commit": {
    "hash": "4f9a8de49e5ed9a8c0702ac34a7e0bc320a73a11",
    "time": 1657983936
  },
  "versions": [
    {
      "tag": "v0.2.0",
      "hash": "4f9a8de49e5ed9a8c0702ac34a7e0bc320a73a11",
      "time": 1657983936
    },
    {
      "tag": "v0.1.1",
      "hash": "b7ca5fc5d0f16c7e7b8a8e769f855cb43d335dbb",
      "time": 1623770513
    },
    {
      "tag": "v0.1.0",
      "hash": "dbd32564b5d0a1ec67c2c6422358cd6f02cf8327",
      "time": 1623170144
    }
  ],
  "tags": [
    "math",
    "statistics",
    "probability",
    "distributions"
  ]
}