{
  "name": "fwrite",
  "url": "https://github.com/pdrb/nim-fwrite",
  "method": "git",
  "description": "Create files of the desired size",
  "license": "MIT",
  "web": "https://github.com/pdrb/nim-fwrite",
  "commit": {
    "hash": "7f4094130169232160720ac30c0d2d79ac3f4a14",
    "time": 1570657291
  },
  "versions": [
    {
      "tag": "v1.0.0",
      "hash": "c366483d46cf98674ad9a0468e59ba07f6ba7180",
      "time": 1569891457
    }
  ],
  "tags": [
    "create,",
    "file,",
    "write,",
    "fwrite"
  ]
}