{
  "name": "gyaric",
  "url": "https://github.com/jiro4989/gyaric",
  "method": "git",
  "description": "gyaric is a module to encode/decode text to unreadable gyaru's text.",
  "license": "MIT",
  "web": "https://github.com/jiro4989/gyaric",
  "versions": [
    {
      "tag": "v1.0.2",
      "hash": "daf1a4dc68dae6b7469197ff92573d6095fbe9f2",
      "time": 1595579408
    },
    {
      "tag": "v1.0.1",
      "hash": "d2dac9438a92519503ffe2d755bd6a7047f7cb7a",
      "time": 1581690660
    },
    {
      "tag": "v1.0.0",
      "hash": "a666016d4995258ec473d8e1473fc79c072d527e",
      "time": 1577811335
    }
  ],
  "tags": [
    "joke",
    "library",
    "cli",
    "gyaru",
    "encoder",
    "text"
  ]
}