{
  "name": "spurdify",
  "url": "https://github.com/paradox460/spurdify",
  "method": "git",
  "description": "Spurdification library and CLI",
  "license": "MIT",
  "web": "https://github.com/paradox460/spurdify",
  "versions": [
    {
      "tag": "v0.1.1",
      "hash": "45a46eeeb69f5bbdab9c27135df8c03aca85ee92",
      "time": 1690345966
    },
    {
      "tag": "v0.1.0",
      "hash": "7e23861a57416324c16f5ca3bd92b0f6a4b9e8df",
      "time": 1690345045
    },
    {
      "tag": "v0.0.6",
      "hash": "5b6d655dfc3b1fcb999d59798218f044095bb114",
      "time": 1590785359
    },
    {
      "tag": "v0.0.5",
      "hash": "ebaa126ac65288ad6afee67a4c8701ff6167686f",
      "time": 1573083657
    },
    {
      "tag": "v0.0.4",
      "hash": "1de2b80e2a0e4034fc26b1275ec8a7943605a8f9",
      "time": 1564964393
    }
  ],
  "tags": [
    "funny",
    "meme",
    "spurdo",
    "text-manipulation",
    "mangle"
  ]
}